{
  "project_info": {
    "project_number": "438566260281",
    "firebase_url": "https://digital-library-290309.firebaseio.com",
    "project_id": "digital-library-290309",
    "storage_bucket": "digital-library-290309.appspot.com"
  },
  "client": [
    {
      "client_info": {
        "mobilesdk_app_id": "1:438566260281:android:1d8228009218b7e5ba07e8",
        "android_client_info": {
          "package_name": "com.library.digitallibrary"
        }
      },
      "oauth_client": [
        {
          "client_id": "438566260281-2dbr28bf1t6pkpqqolgkt9r496iki9uq.apps.googleusercontent.com",
          "client_type": 1,
          "android_info": {
            "package_name": "com.library.digitallibrary",
            "certificate_hash": "5325afa47da13ef981ca17e0134edbfcea3e459d"
          }
        },
        {
          "client_id": "438566260281-n61ed3fgrq0m9302tjs1bnfliibgedhg.apps.googleusercontent.com",
          "client_type": 3
        }
      ],
      "api_key": [
        {
          "current_key": "AIzaSyBKMQG56c9KFQlWgm721ii0pXkr7hTUpTw"
        }
      ],
      "services": {
        "appinvite_service": {
          "other_platform_oauth_client": [
            {
              "client_id": "438566260281-n61ed3fgrq0m9302tjs1bnfliibgedhg.apps.googleusercontent.com",
              "client_type": 3
            }
          ]
        }
      }
    }
  ],
  "configuration_version": "1"
}